ademamix/__init__.py
ademamix/ademamix.py
ademamix/utils.py
ademamix-0.0.1.dist-info/LICENSE
ademamix-0.0.1.dist-info/METADATA
ademamix-0.0.1.dist-info/WHEEL
ademamix-0.0.1.dist-info/RECORD
