Metadata-Version: 2.1
Name: ademamix
Version: 0.0.1
Summary: AdEMAMix is a PyTorch optimizer that combines two EMAs to better utilize past gradients, offering improved convergence and model retention over AdamW.
License: MIT
Author: Oguz Vuruskaner
Author-email: ovuruska@outlook.com
Requires-Python: >=3.8,<4.0
Classifier: License :: OSI Approved :: MIT License
Classifier: Programming Language :: Python :: 3
Classifier: Programming Language :: Python :: 3.8
Classifier: Programming Language :: Python :: 3.9
Classifier: Programming Language :: Python :: 3.10
Classifier: Programming Language :: Python :: 3.11
Classifier: Programming Language :: Python :: 3.12
Requires-Dist: torch (>=2.0.0,<3.0.0)
